motu_osc_bridge/__init__.py
motu_osc_bridge/app.py
motu_osc_bridge/server.py
motu_osc_bridge-0.1.1.dist-info/LICENSE
motu_osc_bridge-0.1.1.dist-info/METADATA
motu_osc_bridge-0.1.1.dist-info/WHEEL
motu_osc_bridge-0.1.1.dist-info/top_level.txt
motu_osc_bridge-0.1.1.dist-info/RECORD
