Metadata-Version: 2.1
Name: motu_osc_bridge
Version: 0.1.1
Summary: A service to bridge HTTP messages from a MOTU AVB interface's datastore API to an OSC Server, such as TouchOSC.
Author-email: Christopher Johnston <christopher_johnston@me.com>
License: MIT License
Project-URL: Homepage, https://github.com/ChristopherJohnston/motu_osc_bridge
Keywords: motu,avb,osc
Classifier: License :: OSI Approved :: MIT License
Classifier: Programming Language :: Python
Classifier: Programming Language :: Python :: 3
Requires-Python: >=3.11
License-File: LICENSE
Requires-Dist: aiohappyeyeballs
Requires-Dist: aiohttp
Requires-Dist: aiosignal
Requires-Dist: asyncio
Requires-Dist: motu-datastore-client
Requires-Dist: python-osc
Requires-Dist: zeroconf
